lesscode_database/__init__.py
lesscode_database/connect_pool.py
lesscode_database/connection_info.py
lesscode_database/db_options.py
lesscode_database/db_request.py
lesscode_database/ds_helper.py
lesscode_database/dynamic_import_package.py
lesscode_database/mongo_base_model.py
lesscode_database/orm/__init__.py
lesscode_database/orm/orm_exec.py
lesscode_database/orm/orm_func.py
lesscode_database/orm/orm_model.py
lesscode_database/orm/orm_typing.py
lesscode_database-0.0.13.dist-info/METADATA
lesscode_database-0.0.13.dist-info/WHEEL
lesscode_database-0.0.13.dist-info/licenses/LICENSE
lesscode_database-0.0.13.dist-info/RECORD
