Metadata-Version: 2.1
Name: lesscode-database
Version: 0.0.13
Summary: lesscode_database是数据库连接工具包
Author-email: navysummer <navysummer@yeah.net>
License: MIT License
License-File: LICENSE
Classifier: License :: OSI Approved :: MIT License
Classifier: Operating System :: OS Independent
Classifier: Programming Language :: Python :: 3
Requires-Python: >=3.7
